pararamio_aio/__init__.py
pararamio_aio/client.py
pararamio_aio/cookie_manager.py
pararamio_aio/exceptions.py
pararamio_aio/file_operations.py
pararamio_aio/py.typed
pararamio_aio/schemas.py
pararamio_aio/types.py
pararamio_aio/_core/__init__.py
pararamio_aio/_core/_types.py
pararamio_aio/_core/client_protocol.py
pararamio_aio/_core/cookie_manager.py
pararamio_aio/_core/endpoints.py
pararamio_aio/_core/py.typed
pararamio_aio/_core/validators.py
pararamio_aio/_core/api_schemas/__init__.py
pararamio_aio/_core/api_schemas/requests/__init__.py
pararamio_aio/_core/api_schemas/requests/chat.py
pararamio_aio/_core/api_schemas/requests/deferred_post.py
pararamio_aio/_core/api_schemas/requests/group.py
pararamio_aio/_core/api_schemas/requests/post.py
pararamio_aio/_core/api_schemas/responses/__init__.py
pararamio_aio/_core/api_schemas/responses/activity.py
pararamio_aio/_core/api_schemas/responses/attachment.py
pararamio_aio/_core/api_schemas/responses/base.py
pararamio_aio/_core/api_schemas/responses/bot.py
pararamio_aio/_core/api_schemas/responses/chat.py
pararamio_aio/_core/api_schemas/responses/common.py
pararamio_aio/_core/api_schemas/responses/deferred_post.py
pararamio_aio/_core/api_schemas/responses/deferred_post_create.py
pararamio_aio/_core/api_schemas/responses/events.py
pararamio_aio/_core/api_schemas/responses/file.py
pararamio_aio/_core/api_schemas/responses/group.py
pararamio_aio/_core/api_schemas/responses/message.py
pararamio_aio/_core/api_schemas/responses/poll.py
pararamio_aio/_core/api_schemas/responses/post.py
pararamio_aio/_core/api_schemas/responses/read_status.py
pararamio_aio/_core/api_schemas/responses/rerere.py
pararamio_aio/_core/api_schemas/responses/team.py
pararamio_aio/_core/api_schemas/responses/user.py
pararamio_aio/_core/constants/__init__.py
pararamio_aio/_core/constants/base.py
pararamio_aio/_core/constants/endpoints.py
pararamio_aio/_core/exceptions/__init__.py
pararamio_aio/_core/exceptions/auth.py
pararamio_aio-3.0.10.dist-info/METADATA
pararamio_aio-3.0.10.dist-info/WHEEL
pararamio_aio-3.0.10.dist-info/top_level.txt
pararamio_aio-3.0.10.dist-info/RECORD
