Metadata-Version: 2.4
Name: pararamio-aio
Version: 3.0.10
Summary: Async Python client library for pararam.io platform
Author: Pararamio Team
License: MIT
Project-URL: Homepage, https://gitlab.com/pararam-public/py-pararamio
Project-URL: Documentation, https://gitlab.com/pararam-public/py-pararamio/-/wikis/home
Project-URL: Repository, https://gitlab.com/pararam-public/py-pararamio
Project-URL: Issues, https://gitlab.com/pararam-public/py-pararamio/-/issues
Classifier: Development Status :: 3 - Alpha
Classifier: Intended Audience :: Developers
Classifier: License :: OSI Approved :: MIT License
Classifier: Programming Language :: Python :: 3
Classifier: Programming Language :: Python :: 3.9
Classifier: Programming Language :: Python :: 3.10
Classifier: Programming Language :: Python :: 3.11
Classifier: Programming Language :: Python :: 3.12
Classifier: Programming Language :: Python :: 3.13
Classifier: Topic :: Internet :: WWW/HTTP
Classifier: Topic :: Software Development :: Libraries :: Python Modules
Requires-Python: >=3.11
Requires-Dist: httpx>=0.25.0
Provides-Extra: dev
Requires-Dist: pytest>=8.4.2; extra == "dev"
Requires-Dist: pytest-asyncio>=1.2.0; extra == "dev"
Requires-Dist: pytest-cov>=7.0.0; extra == "dev"
Requires-Dist: ruff>=0.13.2; extra == "dev"
Requires-Dist: mypy>=1.18.2; extra == "dev"
